aioapp_pg/__init__.py
tests/__init__.py
tests/conftest.py
tests/docker-compose.yml
tests/test_db.py
aioapp_pg-0.0.1b6.dist-info/AUTHORS.rst
aioapp_pg-0.0.1b6.dist-info/LICENSE
aioapp_pg-0.0.1b6.dist-info/METADATA
aioapp_pg-0.0.1b6.dist-info/WHEEL
aioapp_pg-0.0.1b6.dist-info/top_level.txt
aioapp_pg-0.0.1b6.dist-info/RECORD
