Metadata-Version: 2.1
Name: aioapp-pg
Version: 0.0.1b6
Summary: Aioapp adapter for asyncpg
Home-page: https://github.com/inplat/aioapp_pg
Author: Konstantin Stepanov
Author-email: UNKNOWN
License: Apache License 2.0
Keywords: aioapp_pg
Platform: UNKNOWN
Classifier: Development Status :: 2 - Pre-Alpha
Classifier: Intended Audience :: Developers
Classifier: License :: OSI Approved :: Apache Software License
Classifier: Natural Language :: English
Classifier: Programming Language :: Python :: 3
Classifier: Programming Language :: Python :: 3.6
Requires-Dist: aioapp (==0.0.2b8)
Requires-Dist: asyncpg (==0.18.3)
